topsis/__init__.py
topsis/topsis.py
Topsis_Karan_102003355-1.0.8.dist-info/LICENSE.txt
Topsis_Karan_102003355-1.0.8.dist-info/METADATA
Topsis_Karan_102003355-1.0.8.dist-info/WHEEL
Topsis_Karan_102003355-1.0.8.dist-info/entry_points.txt
Topsis_Karan_102003355-1.0.8.dist-info/top_level.txt
Topsis_Karan_102003355-1.0.8.dist-info/RECORD
